skipy/AWS/__init__.py
skipy/AWS/utils.py
skipy/Chatwork/__init__.py
skipy/Chatwork/__wrapper.py
skipy/GCP/__init__.py
skipy/GCP/drive.py
skipy/GCP/sheet.py
skipy/OpenAI/__init__.py
skipy/OpenAI/__wrapper.py
skipy/Selenium/__init__.py
skipy/Selenium/__wrapper.py
skipy/Slack/__init__.py
skipy/Slack/__wrapper.py
skipy/__init__.py
skipy-0.3.2.dist-info/METADATA
skipy-0.3.2.dist-info/WHEEL
skipy-0.3.2.dist-info/RECORD
