Metadata-Version: 2.3
Name: skipy
Version: 0.3.2
Summary: Skip-tac python modules
License: MIT
Author: syamaguc
Author-email: programmer2844@gmail.com
Requires-Python: >=3.8.1,<4.0
Classifier: License :: OSI Approved :: MIT License
Classifier: Programming Language :: Python :: 3
Classifier: Programming Language :: Python :: 3.9
Classifier: Programming Language :: Python :: 3.10
Classifier: Programming Language :: Python :: 3.11
Classifier: Programming Language :: Python :: 3.12
Classifier: Programming Language :: Python :: 3.13
Requires-Dist: boto3 (>=1.29.6,<2.0.0)
Requires-Dist: google-api-python-client (>=2.108.0,<3.0.0)
Requires-Dist: openai (>=1.95.1,<2.0.0)
Requires-Dist: python-magic (>=0.4.27,<0.5.0)
Requires-Dist: requests (>=2.31.0,<3.0.0)
Requires-Dist: selenium (>=4.15.2,<5.0.0)
Requires-Dist: slack-sdk (>=3.34.0,<4.0.0)
